pytular/__init__.py
pytular/util.py
pytular-0.1.0.dist-info/LICENSE
pytular-0.1.0.dist-info/METADATA
pytular-0.1.0.dist-info/WHEEL
pytular-0.1.0.dist-info/top_level.txt
pytular-0.1.0.dist-info/RECORD
